BayesPermus/__init__.py
BayesPermus/figure/__init__.py
BayesPermus/figure/plot.py
BayesPermus/models/Base.py
BayesPermus/models/BradleyTerry.py
BayesPermus/models/MallowsModel.py
BayesPermus/models/PlackettLuce.py
BayesPermus/models/__init__.py
BayesPermus-1.0.0.dist-info/LICENSE
BayesPermus-1.0.0.dist-info/METADATA
BayesPermus-1.0.0.dist-info/WHEEL
BayesPermus-1.0.0.dist-info/top_level.txt
BayesPermus-1.0.0.dist-info/RECORD
