Metadata-Version: 2.1
Name: BayesPermus
Version: 1.0.0
Summary: Bayesian inference of algorithm performance using permutation models.
Home-page: https://github.com/ml-opt/BayesPermus
Author: Jairo Rojas-Delgado
Author-email: jrojasdelgado@bcamath.org
License: UNKNOWN
Project-URL: Bug Tracker, https://github.com/ml-opt/BayesPermus/issues
Platform: UNKNOWN
Classifier: Programming Language :: Python :: 3
Classifier: License :: OSI Approved :: MIT License
Classifier: Operating System :: OS Independent
Requires-Python: >=3.6
License-File: LICENSE
